{
  "project_info": {
    "project_number": "1053550566777",
    "project_id": "testingdb-922f0",
    "storage_bucket": "testingdb-922f0.appspot.com"
  },
  "client": [
    {
      "client_info": {
        "mobilesdk_app_id": "1:1053550566777:android:93f199b038d4c82ccba3a8",
        "android_client_info": {
          "package_name": "com.franzandel.firestoretutorial"
        }
      },
      "oauth_client": [
        {
          "client_id": "1053550566777-40ds001lf452lr717i5sod08otum12k0.apps.googleusercontent.com",
          "client_type": 3
        }
      ],
      "api_key": [
        {
          "current_key": "AIzaSyD2s06XZhKPoJO9sVIQWpj3rZeUdKfzFSM"
        }
      ],
      "services": {
        "appinvite_service": {
          "other_platform_oauth_client": [
            {
              "client_id": "1053550566777-40ds001lf452lr717i5sod08otum12k0.apps.googleusercontent.com",
              "client_type": 3
            }
          ]
        }
      }
    },
    {
      "client_info": {
        "mobilesdk_app_id": "1:1053550566777:android:4cee8cf5cdd3078ecba3a8",
        "android_client_info": {
          "package_name": "com.franzandel.rtdbtutorial"
        }
      },
      "oauth_client": [
        {
          "client_id": "1053550566777-40ds001lf452lr717i5sod08otum12k0.apps.googleusercontent.com",
          "client_type": 3
        }
      ],
      "api_key": [
        {
          "current_key": "AIzaSyD2s06XZhKPoJO9sVIQWpj3rZeUdKfzFSM"
        }
      ],
      "services": {
        "appinvite_service": {
          "other_platform_oauth_client": [
            {
              "client_id": "1053550566777-40ds001lf452lr717i5sod08otum12k0.apps.googleusercontent.com",
              "client_type": 3
            }
          ]
        }
      }
    }
  ],
  "configuration_version": "1"
}